vcs_scraper/__init__.py
vcs_scraper/common.py
vcs_scraper/configuration.py
vcs_scraper/constants.py
vcs_scraper/dict_remapper.py
vcs_scraper/environment_wrapper.py
vcs_scraper/model.py
vcs_scraper/vcs_instances_parser.py
vcs_scraper/project_collector/__init__.py
vcs_scraper/project_collector/common.py
vcs_scraper/repository_collector/__init__.py
vcs_scraper/repository_collector/common.py
vcs_scraper/static/logging.ini
vcs_scraper/vcs_connectors/__init__.py
vcs_scraper/vcs_connectors/azure_devops_connector.py
vcs_scraper/vcs_connectors/azure_devops_data_mapper.py
vcs_scraper/vcs_connectors/bitbucket_connector.py
vcs_scraper/vcs_connectors/bitbucket_data_mapper.py
vcs_scraper/vcs_connectors/github_public_connector.py
vcs_scraper/vcs_connectors/vcs_connector.py
vcs_scraper/vcs_connectors/vcs_connector_factory.py
vcs_scraper-1.0.0.dist-info/METADATA
vcs_scraper-1.0.0.dist-info/WHEEL
vcs_scraper-1.0.0.dist-info/entry_points.txt
vcs_scraper-1.0.0.dist-info/top_level.txt
vcs_scraper-1.0.0.dist-info/RECORD
