Metadata-Version: 2.1
Name: vcs-scraper
Version: 1.0.0
Summary: Repository Scanner -- Version Control Systems' scraper
Home-page: https://github.com/ABNAMRO/repository-scanner
Author: ABN AMRO
Author-email: resc@nl.abnamro.com
License: UNKNOWN
Platform: UNKNOWN
Requires-Dist: celery (==5.2.3)
Requires-Dist: atlassian-python-api (==3.10.0)
Requires-Dist: requests (==2.25.1)
Requires-Dist: azure-devops (==6.0.0b4)
Requires-Dist: tenacity (==8.0.1)
Requires-Dist: pydantic (==1.8.2)
Requires-Dist: pygithub (==1.55)
